README.md
setup.py
losd/__init__.py
losd/access.py
losd/utils.py
losd.egg-info/PKG-INFO
losd.egg-info/SOURCES.txt
losd.egg-info/dependency_links.txt
losd.egg-info/requires.txt
losd.egg-info/top_level.txt