Metadata-Version: 2.1
Name: losd
Version: 0.2b0
Summary: losd is (currently) a very simple python package for querying the LOSD (linked open social data) dataset
Home-page: https://github.com/ttm/losd
Author: Renato Fabbri
Author-email: renato.fabbri@gmail.com
License: MIT
Keywords: physics,complex networks,social networks,text,language,linked data
Platform: UNKNOWN
Classifier: Development Status :: 4 - Beta
Classifier: Intended Audience :: Science/Research
Classifier: Intended Audience :: Developers
Classifier: Intended Audience :: Education
Classifier: Intended Audience :: Other Audience
Classifier: Topic :: Scientific/Engineering :: Physics
Classifier: Topic :: Scientific/Engineering :: Visualization
Classifier: Topic :: Scientific/Engineering :: Information Analysis
Classifier: Topic :: Artistic Software
Classifier: Topic :: Other/Nonlisted Topic
Classifier: Topic :: Text Processing
Classifier: Topic :: Text Processing :: Linguistic
Classifier: Topic :: System :: Networking
Classifier: License :: CC0 1.0 Universal (CC0 1.0) Public Domain Dedication
Classifier: Programming Language :: Python :: 3
Classifier: Programming Language :: Python :: 2
